pulumi_equinix_metal/__init__.py
pulumi_equinix_metal/_enums.py
pulumi_equinix_metal/_inputs.py
pulumi_equinix_metal/_utilities.py
pulumi_equinix_metal/bgp_session.py
pulumi_equinix_metal/connection.py
pulumi_equinix_metal/device.py
pulumi_equinix_metal/device_network_type.py
pulumi_equinix_metal/gateway.py
pulumi_equinix_metal/get_connection.py
pulumi_equinix_metal/get_device.py
pulumi_equinix_metal/get_device_bgp_neighbors.py
pulumi_equinix_metal/get_facility.py
pulumi_equinix_metal/get_gateway.py
pulumi_equinix_metal/get_hardware_reservation.py
pulumi_equinix_metal/get_ip_block_ranges.py
pulumi_equinix_metal/get_metro.py
pulumi_equinix_metal/get_operating_system.py
pulumi_equinix_metal/get_organization.py
pulumi_equinix_metal/get_port.py
pulumi_equinix_metal/get_precreated_ip_block.py
pulumi_equinix_metal/get_project.py
pulumi_equinix_metal/get_project_ssh_key.py
pulumi_equinix_metal/get_reserved_ip_block.py
pulumi_equinix_metal/get_spot_market_price.py
pulumi_equinix_metal/get_spot_market_request.py
pulumi_equinix_metal/get_virtual_circuit.py
pulumi_equinix_metal/get_vlan.py
pulumi_equinix_metal/get_volume.py
pulumi_equinix_metal/ip_attachment.py
pulumi_equinix_metal/organization.py
pulumi_equinix_metal/outputs.py
pulumi_equinix_metal/port.py
pulumi_equinix_metal/port_vlan_attachment.py
pulumi_equinix_metal/project.py
pulumi_equinix_metal/project_api_key.py
pulumi_equinix_metal/project_ssh_key.py
pulumi_equinix_metal/provider.py
pulumi_equinix_metal/pulumi-plugin.json
pulumi_equinix_metal/py.typed
pulumi_equinix_metal/reserved_ip_block.py
pulumi_equinix_metal/spot_market_request.py
pulumi_equinix_metal/ssh_key.py
pulumi_equinix_metal/user_api_key.py
pulumi_equinix_metal/virtual_circuit.py
pulumi_equinix_metal/vlan.py
pulumi_equinix_metal/volume.py
pulumi_equinix_metal/volume_attachment.py
pulumi_equinix_metal/config/__init__.py
pulumi_equinix_metal/config/vars.py
pulumi_equinix_metal-3.3.0a1696874530.dist-info/METADATA
pulumi_equinix_metal-3.3.0a1696874530.dist-info/WHEEL
pulumi_equinix_metal-3.3.0a1696874530.dist-info/top_level.txt
pulumi_equinix_metal-3.3.0a1696874530.dist-info/RECORD
