Metadata-Version: 2.1
Name: pulumi-equinix-metal
Version: 3.3.0a1696874530
Summary: A Pulumi package for creating and managing equinix-metal cloud resources.
License: Apache-2.0
Project-URL: Homepage, https://pulumi.io
Project-URL: Repository, https://github.com/pulumi/pulumi-equinix-metal
Keywords: pulumi,equinix-metal
Requires-Python: >=3.7
Requires-Dist: parver >=0.2.1
Requires-Dist: pulumi <4.0.0,>=3.0.0
Requires-Dist: semver >=2.8.1
